{
  "version": 1,
  "docs": {
    "projectContext": {
      "path": "docs/05_process/project-context.md",
      "title": "项目上下文（硬约束）",
      "maxChars": 9000
    },
    "dod": {
      "path": "docs/05_process/definition-of-done.md",
      "title": "DoD（完成定义）",
      "maxChars": 9000
    }
  },
  "defaults": ["projectContext"],
  "stepKinds": {
    "code.review": ["dod"],
    "prd.review": ["dod"],
    "pr.create": ["dod"],
    "pr.merge": ["dod"],
    "ci.gate": ["dod"],
    "report.publish": ["dod"]
  }
}
